metriport/__init__.py
metriport/client.py
metriport/commons/__init__.py
metriport/commons/types/__init__.py
metriport/commons/types/address.py
metriport/commons/types/us_state.py
metriport/core/__init__.py
metriport/core/api_error.py
metriport/core/client_wrapper.py
metriport/core/datetime_utils.py
metriport/core/file.py
metriport/core/http_client.py
metriport/core/jsonable_encoder.py
metriport/core/pydantic_utilities.py
metriport/core/query_encoder.py
metriport/core/remove_none_from_dict.py
metriport/core/request_options.py
metriport/core/serialization.py
metriport/environment.py
metriport/fhir/__init__.py
metriport/fhir/types/__init__.py
metriport/fhir/types/access_policy.py
metriport/fhir/types/access_policy_ip_access_rule.py
metriport/fhir/types/access_policy_ip_access_rule_action.py
metriport/fhir/types/access_policy_resource.py
metriport/fhir/types/access_policy_resource_write_criteria.py
metriport/fhir/types/account.py
metriport/fhir/types/account_coverage.py
metriport/fhir/types/account_guarantor.py
metriport/fhir/types/account_status.py
metriport/fhir/types/activity_definition.py
metriport/fhir/types/activity_definition_dynamic_value.py
metriport/fhir/types/activity_definition_participant.py
metriport/fhir/types/activity_definition_status.py
metriport/fhir/types/address.py
metriport/fhir/types/address_type.py
metriport/fhir/types/address_use.py
metriport/fhir/types/adverse_event.py
metriport/fhir/types/adverse_event_actuality.py
metriport/fhir/types/adverse_event_causality.py
metriport/fhir/types/adverse_event_suspect_entity.py
metriport/fhir/types/age.py
metriport/fhir/types/age_comparator.py
metriport/fhir/types/agent.py
metriport/fhir/types/agent_channel.py
metriport/fhir/types/agent_setting.py
metriport/fhir/types/agent_status.py
metriport/fhir/types/allergy_intolerance.py
metriport/fhir/types/allergy_intolerance_category_item.py
metriport/fhir/types/allergy_intolerance_criticality.py
metriport/fhir/types/allergy_intolerance_reaction.py
metriport-9.1.1.dist-info/METADATA
metriport-9.1.1.dist-info/WHEEL
metriport-9.1.1.dist-info/RECORD
