Metadata-Version: 2.3
Name: metriport
Version: 9.1.1
Summary: 
Requires-Python: >=3.11,<4.0
Classifier: Programming Language :: Python :: 3
Classifier: Programming Language :: Python :: 3.11
Classifier: Programming Language :: Python :: 3.12
Classifier: Programming Language :: Python :: 3.13
Requires-Dist: fastapi (>=0.109.1,<0.110.0)
Requires-Dist: httpx (>=0.21.2)
Requires-Dist: pydantic (>=1.9.2,<2.5.0)
Requires-Dist: python-dotenv (>=1.0.0,<2.0.0)
